{
  "name": "dnt/测试1-短剑",
  "starLevel": 5,
  "type": 1,
  "stats": {
    "0": {
      "1": [
        {
          "name": "攻击",
          "value": 56.0,
          "isRatio": false,
          "isPercent": false
        },
        {
          "name": "暴击",
          "value": 540.0,
          "isRatio": false,
          "isPercent": true
        }
      ],
      "2": [
        {
          "name": "攻击",
          "value": 60.7152,
          "isRatio": false,
          "isPercent": false
        },
        {
          "name": "暴击",
          "value": 540.0,
          "isRatio": false,
          "isPercent": true
        }
      ],
      "3": [
        {
          "name": "攻击",
          "value": 65.436,
          "isRatio": false,
          "isPercent": false
        },
        {
          "name": "暴击",
          "value": 540.0,
          "isRatio": false,
          "isPercent": true
        }
      ],
      "4": [
        {
          "name": "攻击",
          "value": 70.1568,
          "isRatio": false,
          "isPercent": false
        },
        {
          "name": "暴击",
          "value": 540.0,
          "isRatio": false,
          "isPercent": true
        }
      ],
      "5": [
        {
          "name": "攻击",
          "value": 74.872,
          "isRatio": false,
          "isPercent": false
        },
        {
          "name": "暴击",
          "value": 644.976,
          "isRatio": false,
          "isPercent": true
        }
      ],
      "6": [
        {
          "name": "攻击",
          "value": 79.5928,
          "isRatio": false,
          "isPercent": false
        },
        {
          "name": "暴击",
          "value": 644.976,
          "isRatio": false,
          "isPercent": true
        }
      ],
      "7": [
        {
          "name": "攻击",
          "value": 84.3136,
          "isRatio": false,
          "isPercent": false
        },
        {
          "name": "暴击",
          "value": 644.976,
          "isRatio": false,
          "isPercent": true
        }
      ],
      "8": [
        {
          "name": "攻击",
          "value": 89.0288,
          "isRatio": false,
          "isPercent": false
        },
        {
          "name": "暴击",
          "value": 644.976,
          "isRatio": false,
          "isPercent": true
        }
      ],
      "9": [
        {
          "name": "攻击",
          "value": 93.7496,
          "isRatio": false,
          "isPercent": false
        },
        {
          "name": "暴击",
          "value": 644.976,
          "isRatio": false,
          "isPercent": true
        }
      ],
      "10": [
        {
          "name": "攻击",
          "value": 98.4704,
          "isRatio": false,
          "isPercent": false
        },
        {
          "name": "暴击",
          "value": 749.952,
          "isRatio": false,
          "isPercent": true
        }
      ],
      "11": [
        {
          "name": "攻击",
          "value": 103.1856,
          "isRatio": false,
          "isPercent": false
        },
        {
          "name": "暴击",
          "value": 749.952,
          "isRatio": false,
          "isPercent": true
        }
      ],
      "12": [
        {
          "name": "攻击",
          "value": 107.9064,
          "isRatio": false,
          "isPercent": false
        },
        {
          "name": "暴击",
          "value": 749.952,
          "isRatio": false,
          "isPercent": true
        }
      ],
      "13": [
        {
          "name": "攻击",
          "value": 112.6272,
          "isRatio": false,
          "isPercent": false
        },
        {
          "name": "暴击",
          "value": 749.952,
          "isRatio": false,
          "isPercent": true
        }
      ],
      "14": [
        {
          "name": "攻击",
          "value": 117.348,
          "isRatio": false,
          "isPercent": false
        },
        {
          "name": "暴击",
          "value": 749.952,
          "isRatio": false,
          "isPercent": true
        }
      ],
      "15": [
        {
          "name": "攻击",
          "value": 122.0632,
          "isRatio": false,
          "isPercent": false
        },
        {
          "name": "暴击",
          "value": 854.982,
          "isRatio": false,
          "isPercent": true
        }
      ],
      "16": [
        {
          "name": "攻击",
          "value": 126.784,
          "isRatio": false,
          "isPercent": false
        },
        {
          "name": "暴击",
          "value": 854.982,
          "isRatio": false,
          "isPercent": true
        }
      ],
      "17": [
        {
          "name": "攻击",
          "value": 131.5048,
          "isRatio": false,
          "isPercent": false
        },
        {
          "name": "暴击",
          "value": 854.982,
          "isRatio": false,
          "isPercent": true
        }
      ],
      "18": [
        {
          "name": "攻击",
          "value": 136.22,
          "isRatio": false,
          "isPercent": false
        },
        {
          "name": "暴击",
          "value": 854.982,
          "isRatio": false,
          "isPercent": true
        }
      ],
      "19": [
        {
          "name": "攻击",
          "value": 140.9408,
          "isRatio": false,
          "isPercent": false
        },
        {
          "name": "暴击",
          "value": 854.982,
          "isRatio": false,
          "isPercent": true
        }
      ],
      "20": [
        {
          "name": "攻击",
          "value": 145.6616,
          "isRatio": false,
          "isPercent": false
        },
        {
          "name": "暴击",
          "value": 959.958,
          "isRatio": false,
          "isPercent": true
        }
      ]
    },
    "1": {
      "20": [
        {
          "name": "攻击",
          "value": 182.9912,
          "isRatio": false,
          "isPercent": false
        },
        {
          "name": "暴击",
          "value": 959.958,
          "isRatio": false,
          "isPercent": true
        }
      ],
      "21": [
        {
          "name": "攻击",
          "value": 187.712,
          "isRatio": false,
          "isPercent": false
        },
        {
          "name": "暴击",
          "value": 959.958,
          "isRatio": false,
          "isPercent": true
        }
      ],
      "22": [
        {
          "name": "攻击",
          "value": 192.4328,
          "isRatio": false,
          "isPercent": false
        },
        {
          "name": "暴击",
          "value": 959.958,
          "isRatio": false,
          "isPercent": true
        }
      ],
      "23": [
        {
          "name": "攻击",
          "value": 197.148,
          "isRatio": false,
          "isPercent": false
        },
        {
          "name": "暴击",
          "value": 959.958,
          "isRatio": false,
          "isPercent": true
        }
      ],
      "24": [
        {
          "name": "攻击",
          "value": 201.8688,
          "isRatio": false,
          "isPercent": false
        },
        {
          "name": "暴击",
          "value": 959.958,
          "isRatio": false,
          "isPercent": true
        }
      ],
      "25": [
        {
          "name": "攻击",
          "value": 206.5896,
          "isRatio": false,
          "isPercent": false
        },
        {
          "name": "暴击",
          "value": 1064.988,
          "isRatio": false,
          "isPercent": true
        }
      ],
      "26": [
        {
          "name": "攻击",
          "value": 211.3104,
          "isRatio": false,
          "isPercent": false
        },
        {
          "name": "暴击",
          "value": 1064.988,
          "isRatio": false,
          "isPercent": true
        }
      ],
      "27": [
        {
          "name": "攻击",
          "value": 216.0256,
          "isRatio": false,
          "isPercent": false
        },
        {
          "name": "暴击",
          "value": 1064.988,
          "isRatio": false,
          "isPercent": true
        }
      ],
      "28": [
        {
          "name": "攻击",
          "value": 220.7464,
          "isRatio": false,
          "isPercent": false
        },
        {
          "name": "暴击",
          "value": 1064.988,
          "isRatio": false,
          "isPercent": true
        }
      ],
      "29": [
        {
          "name": "攻击",
          "value": 225.4672,
          "isRatio": false,
          "isPercent": false
        },
        {
          "name": "暴击",
          "value": 1064.988,
          "isRatio": false,
          "isPercent": true
        }
      ],
      "30": [
        {
          "name": "攻击",
          "value": 230.1824,
          "isRatio": false,
          "isPercent": false
        },
        {
          "name": "暴击",
          "value": 1169.964,
          "isRatio": false,
          "isPercent": true
        }
      ],
      "31": [
        {
          "name": "攻击",
          "value": 234.9032,
          "isRatio": false,
          "isPercent": false
        },
        {
          "name": "暴击",
          "value": 1169.964,
          "isRatio": false,
          "isPercent": true
        }
      ],
      "32": [
        {
          "name": "攻击",
          "value": 239.624,
          "isRatio": false,
          "isPercent": false
        },
        {
          "name": "暴击",
          "value": 1169.964,
          "isRatio": false,
          "isPercent": true
        }
      ],
      "33": [
        {
          "name": "攻击",
          "value": 244.3392,
          "isRatio": false,
          "isPercent": false
        },
        {
          "name": "暴击",
          "value": 1169.964,
          "isRatio": false,
          "isPercent": true
        }
      ],
      "34": [
        {
          "name": "攻击",
          "value": 249.06,
          "isRatio": false,
          "isPercent": false
        },
        {
          "name": "暴击",
          "value": 1169.964,
          "isRatio": false,
          "isPercent": true
        }
      ],
      "35": [
        {
          "name": "攻击",
          "value": 253.7808,
          "isRatio": false,
          "isPercent": false
        },
        {
          "name": "暴击",
          "value": 1274.994,
          "isRatio": false,
          "isPercent": true
        }
      ],
      "36": [
        {
          "name": "攻击",
          "value": 258.5016,
          "isRatio": false,
          "isPercent": false
        },
        {
          "name": "暴击",
          "value": 1274.994,
          "isRatio": false,
          "isPercent": true
        }
      ],
      "37": [
        {
          "name": "攻击",
          "value": 263.2168,
          "isRatio": false,
          "isPercent": false
        },
        {
          "name": "暴击",
          "value": 1274.994,
          "isRatio": false,
          "isPercent": true
        }
      ],
      "38": [
        {
          "name": "攻击",
          "value": 267.9376,
          "isRatio": false,
          "isPercent": false
        },
        {
          "name": "暴击",
          "value": 1274.994,
          "isRatio": false,
          "isPercent": true
        }
      ],
      "39": [
        {
          "name": "攻击",
          "value": 272.6584,
          "isRatio": false,
          "isPercent": false
        },
        {
          "name": "暴击",
          "value": 1274.994,
          "isRatio": false,
          "isPercent": true
        }
      ],
      "40": [
        {
          "name": "攻击",
          "value": 277.3736,
          "isRatio": false,
          "isPercent": false
        },
        {
          "name": "暴击",
          "value": 1379.97,
          "isRatio": false,
          "isPercent": true
        }
      ]
    },
    "2": {
      "40": [
        {
          "name": "攻击",
          "value": 314.7088,
          "isRatio": false,
          "isPercent": false
        },
        {
          "name": "暴击",
          "value": 1379.97,
          "isRatio": false,
          "isPercent": true
        }
      ],
      "41": [
        {
          "name": "攻击",
          "value": 319.4296,
          "isRatio": false,
          "isPercent": false
        },
        {
          "name": "暴击",
          "value": 1379.97,
          "isRatio": false,
          "isPercent": true
        }
      ],
      "42": [
        {
          "name": "攻击",
          "value": 324.1448,
          "isRatio": false,
          "isPercent": false
        },
        {
          "name": "暴击",
          "value": 1379.97,
          "isRatio": false,
          "isPercent": true
        }
      ],
      "43": [
        {
          "name": "攻击",
          "value": 328.8656,
          "isRatio": false,
          "isPercent": false
        },
        {
          "name": "暴击",
          "value": 1379.97,
          "isRatio": false,
          "isPercent": true
        }
      ],
      "44": [
        {
          "name": "攻击",
          "value": 333.5864,
          "isRatio": false,
          "isPercent": false
        },
        {
          "name": "暴击",
          "value": 1379.97,
          "isRatio": false,
          "isPercent": true
        }
      ],
      "45": [
        {
          "name": "攻击",
          "value": 338.3016,
          "isRatio": false,
          "isPercent": false
        },
        {
          "name": "暴击",
          "value": 1485.0,
          "isRatio": false,
          "isPercent": true
        }
      ],
      "46": [
        {
          "name": "攻击",
          "value": 343.0224,
          "isRatio": false,
          "isPercent": false
        },
        {
          "name": "暴击",
          "value": 1485.0,
          "isRatio": false,
          "isPercent": true
        }
      ],
      "47": [
        {
          "name": "攻击",
          "value": 347.7432,
          "isRatio": false,
          "isPercent": false
        },
        {
          "name": "暴击",
          "value": 1485.0,
          "isRatio": false,
          "isPercent": true
        }
      ],
      "48": [
        {
          "name": "攻击",
          "value": 352.464,
          "isRatio": false,
          "isPercent": false
        },
        {
          "name": "暴击",
          "value": 1485.0,
          "isRatio": false,
          "isPercent": true
        }
      ],
      "49": [
        {
          "name": "攻击",
          "value": 357.1792,
          "isRatio": false,
          "isPercent": false
        },
        {
          "name": "暴击",
          "value": 1485.0,
          "isRatio": false,
          "isPercent": true
        }
      ],
      "50": [
        {
          "name": "攻击",
          "value": 361.9,
          "isRatio": false,
          "isPercent": false
        },
        {
          "name": "暴击",
          "value": 1589.976,
          "isRatio": false,
          "isPercent": true
        }
      ]
    },
    "3": {
      "50": [
        {
          "name": "攻击",
          "value": 399.2352,
          "isRatio": false,
          "isPercent": false
        },
        {
          "name": "暴击",
          "value": 1589.976,
          "isRatio": false,
          "isPercent": true
        }
      ],
      "51": [
        {
          "name": "攻击",
          "value": 403.9504,
          "isRatio": false,
          "isPercent": false
        },
        {
          "name": "暴击",
          "value": 1589.976,
          "isRatio": false,
          "isPercent": true
        }
      ],
      "52": [
        {
          "name": "攻击",
          "value": 408.6712,
          "isRatio": false,
          "isPercent": false
        },
        {
          "name": "暴击",
          "value": 1589.976,
          "isRatio": false,
          "isPercent": true
        }
      ],
      "53": [
        {
          "name": "攻击",
          "value": 413.392,
          "isRatio": false,
          "isPercent": false
        },
        {
          "name": "暴击",
          "value": 1589.976,
          "isRatio": false,
          "isPercent": true
        }
      ],
      "54": [
        {
          "name": "攻击",
          "value": 418.1072,
          "isRatio": false,
          "isPercent": false
        },
        {
          "name": "暴击",
          "value": 1589.976,
          "isRatio": false,
          "isPercent": true
        }
      ],
      "55": [
        {
          "name": "攻击",
          "value": 422.828,
          "isRatio": false,
          "isPercent": false
        },
        {
          "name": "暴击",
          "value": 1694.952,
          "isRatio": false,
          "isPercent": true
        }
      ],
      "56": [
        {
          "name": "攻击",
          "value": 427.5488,
          "isRatio": false,
          "isPercent": false
        },
        {
          "name": "暴击",
          "value": 1694.952,
          "isRatio": false,
          "isPercent": true
        }
      ],
      "57": [
        {
          "name": "攻击",
          "value": 432.2696,
          "isRatio": false,
          "isPercent": false
        },
        {
          "name": "暴击",
          "value": 1694.952,
          "isRatio": false,
          "isPercent": true
        }
      ],
      "58": [
        {
          "name": "攻击",
          "value": 436.9848,
          "isRatio": false,
          "isPercent": false
        },
        {
          "name": "暴击",
          "value": 1694.952,
          "isRatio": false,
          "isPercent": true
        }
      ],
      "59": [
        {
          "name": "攻击",
          "value": 441.7056,
          "isRatio": false,
          "isPercent": false
        },
        {
          "name": "暴击",
          "value": 1694.952,
          "isRatio": false,
          "isPercent": true
        }
      ],
      "60": [
        {
          "name": "攻击",
          "value": 446.4264,
          "isRatio": false,
          "isPercent": false
        },
        {
          "name": "暴击",
          "value": 1799.982,
          "isRatio": false,
          "isPercent": true
        }
      ]
    },
    "4": {
      "60": [
        {
          "name": "攻击",
          "value": 483.756,
          "isRatio": false,
          "isPercent": false
        },
        {
          "name": "暴击",
          "value": 1799.982,
          "isRatio": false,
          "isPercent": true
        }
      ],
      "61": [
        {
          "name": "攻击",
          "value": 488.4768,
          "isRatio": false,
          "isPercent": false
        },
        {
          "name": "暴击",
          "value": 1799.982,
          "isRatio": false,
          "isPercent": true
        }
      ],
      "62": [
        {
          "name": "攻击",
          "value": 493.1976,
          "isRatio": false,
          "isPercent": false
        },
        {
          "name": "暴击",
          "value": 1799.982,
          "isRatio": false,
          "isPercent": true
        }
      ],
      "63": [
        {
          "name": "攻击",
          "value": 497.9128,
          "isRatio": false,
          "isPercent": false
        },
        {
          "name": "暴击",
          "value": 1799.982,
          "isRatio": false,
          "isPercent": true
        }
      ],
      "64": [
        {
          "name": "攻击",
          "value": 502.6336,
          "isRatio": false,
          "isPercent": false
        },
        {
          "name": "暴击",
          "value": 1799.982,
          "isRatio": false,
          "isPercent": true
        }
      ],
      "65": [
        {
          "name": "攻击",
          "value": 507.3544,
          "isRatio": false,
          "isPercent": false
        },
        {
          "name": "暴击",
          "value": 1904.958,
          "isRatio": false,
          "isPercent": true
        }
      ],
      "66": [
        {
          "name": "攻击",
          "value": 512.0696,
          "isRatio": false,
          "isPercent": false
        },
        {
          "name": "暴击",
          "value": 1904.958,
          "isRatio": false,
          "isPercent": true
        }
      ],
      "67": [
        {
          "name": "攻击",
          "value": 516.7904,
          "isRatio": false,
          "isPercent": false
        },
        {
          "name": "暴击",
          "value": 1904.958,
          "isRatio": false,
          "isPercent": true
        }
      ],
      "68": [
        {
          "name": "攻击",
          "value": 521.5112,
          "isRatio": false,
          "isPercent": false
        },
        {
          "name": "暴击",
          "value": 1904.958,
          "isRatio": false,
          "isPercent": true
        }
      ],
      "69": [
        {
          "name": "攻击",
          "value": 526.232,
          "isRatio": false,
          "isPercent": false
        },
        {
          "name": "暴击",
          "value": 1904.958,
          "isRatio": false,
          "isPercent": true
        }
      ],
      "70": [
        {
          "name": "攻击",
          "value": 530.9472,
          "isRatio": false,
          "isPercent": false
        },
        {
          "name": "暴击",
          "value": 2009.988,
          "isRatio": false,
          "isPercent": true
        }
      ]
    },
    "5": {
      "70": [
        {
          "name": "攻击",
          "value": 568.2824,
          "isRatio": false,
          "isPercent": false
        },
        {
          "name": "暴击",
          "value": 2009.988,
          "isRatio": false,
          "isPercent": true
        }
      ],
      "71": [
        {
          "name": "攻击",
          "value": 573.0032,
          "isRatio": false,
          "isPercent": false
        },
        {
          "name": "暴击",
          "value": 2009.988,
          "isRatio": false,
          "isPercent": true
        }
      ],
      "72": [
        {
          "name": "攻击",
          "value": 577.7184,
          "isRatio": false,
          "isPercent": false
        },
        {
          "name": "暴击",
          "value": 2009.988,
          "isRatio": false,
          "isPercent": true
        }
      ],
      "73": [
        {
          "name": "攻击",
          "value": 582.4392,
          "isRatio": false,
          "isPercent": false
        },
        {
          "name": "暴击",
          "value": 2009.988,
          "isRatio": false,
          "isPercent": true
        }
      ],
      "74": [
        {
          "name": "攻击",
          "value": 587.16,
          "isRatio": false,
          "isPercent": false
        },
        {
          "name": "暴击",
          "value": 2009.988,
          "isRatio": false,
          "isPercent": true
        }
      ],
      "75": [
        {
          "name": "攻击",
          "value": 591.8752,
          "isRatio": false,
          "isPercent": false
        },
        {
          "name": "暴击",
          "value": 2114.964,
          "isRatio": false,
          "isPercent": true
        }
      ],
      "76": [
        {
          "name": "攻击",
          "value": 596.596,
          "isRatio": false,
          "isPercent": false
        },
        {
          "name": "暴击",
          "value": 2114.964,
          "isRatio": false,
          "isPercent": true
        }
      ],
      "77": [
        {
          "name": "攻击",
          "value": 601.3168,
          "isRatio": false,
          "isPercent": false
        },
        {
          "name": "暴击",
          "value": 2114.964,
          "isRatio": false,
          "isPercent": true
        }
      ],
      "78": [
        {
          "name": "攻击",
          "value": 606.032,
          "isRatio": false,
          "isPercent": false
        },
        {
          "name": "暴击",
          "value": 2114.964,
          "isRatio": false,
          "isPercent": true
        }
      ],
      "79": [
        {
          "name": "攻击",
          "value": 610.7528,
          "isRatio": false,
          "isPercent": false
        },
        {
          "name": "暴击",
          "value": 2114.964,
          "isRatio": false,
          "isPercent": true
        }
      ],
      "80": [
        {
          "name": "攻击",
          "value": 615.4736,
          "isRatio": false,
          "isPercent": false
        },
        {
          "name": "暴击",
          "value": 2219.994,
          "isRatio": false,
          "isPercent": true
        }
      ]
    },
    "6": {
      "80": [
        {
          "name": "攻击",
          "value": 652.8088,
          "isRatio": false,
          "isPercent": false
        },
        {
          "name": "暴击",
          "value": 2219.994,
          "isRatio": false,
          "isPercent": true
        }
      ],
      "81": [
        {
          "name": "攻击",
          "value": 657.524,
          "isRatio": false,
          "isPercent": false
        },
        {
          "name": "暴击",
          "value": 2219.994,
          "isRatio": false,
          "isPercent": true
        }
      ],
      "82": [
        {
          "name": "攻击",
          "value": 662.2448,
          "isRatio": false,
          "isPercent": false
        },
        {
          "name": "暴击",
          "value": 2219.994,
          "isRatio": false,
          "isPercent": true
        }
      ],
      "83": [
        {
          "name": "攻击",
          "value": 666.9656,
          "isRatio": false,
          "isPercent": false
        },
        {
          "name": "暴击",
          "value": 2219.994,
          "isRatio": false,
          "isPercent": true
        }
      ],
      "84": [
        {
          "name": "攻击",
          "value": 671.6808,
          "isRatio": false,
          "isPercent": false
        },
        {
          "name": "暴击",
          "value": 2219.994,
          "isRatio": false,
          "isPercent": true
        }
      ],
      "85": [
        {
          "name": "攻击",
          "value": 676.4016,
          "isRatio": false,
          "isPercent": false
        },
        {
          "name": "暴击",
          "value": 2324.97,
          "isRatio": false,
          "isPercent": true
        }
      ],
      "86": [
        {
          "name": "攻击",
          "value": 681.1224,
          "isRatio": false,
          "isPercent": false
        },
        {
          "name": "暴击",
          "value": 2324.97,
          "isRatio": false,
          "isPercent": true
        }
      ],
      "87": [
        {
          "name": "攻击",
          "value": 685.8376,
          "isRatio": false,
          "isPercent": false
        },
        {
          "name": "暴击",
          "value": 2324.97,
          "isRatio": false,
          "isPercent": true
        }
      ],
      "88": [
        {
          "name": "攻击",
          "value": 690.5584,
          "isRatio": false,
          "isPercent": false
        },
        {
          "name": "暴击",
          "value": 2324.97,
          "isRatio": false,
          "isPercent": true
        }
      ],
      "89": [
        {
          "name": "攻击",
          "value": 695.2792,
          "isRatio": false,
          "isPercent": false
        },
        {
          "name": "暴击",
          "value": 2324.97,
          "isRatio": false,
          "isPercent": true
        }
      ],
      "90": [
        {
          "name": "攻击",
          "value": 700.0,
          "isRatio": false,
          "isPercent": false
        },
        {
          "name": "暴击",
          "value": 2430.0,
          "isRatio": false,
          "isPercent": true
        }
      ]
    }
  },
  "effect": "存在异常，如有疑问请联系官方客服",
  "effectName": "启程",
  "param": [
    [
      "4",
      "5",
      "6",
      "7",
      "8"
    ]
  ],
  "desc": "存在异常，如有疑问请联系官方客服"
}