{
    "Id": 390070105,
    "Code": "H15-",
    "Name": "寒霜陆龟",
    "Type": "异变植物",
    "Intensity": "轻波级",
    "Place": "瑝珑",
    "Icon": "/Game/Aki/UI/UIResources/Common/Image/IconMonsterGoods/T_IconMonsterGoods_969_UI.T_IconMonsterGoods_969_UI",
    "Skill": {
        "Desc": "使用声骸技能，幻形为寒霜陆龟，同时缓慢回复生命值。幻形过程中再次使用声骸技能可退出幻形状态。\n技能冷却：{0}秒",
        "SimpleDesc": "幻形为寒霜陆龟，期间缓慢回复生命值。",
        "Param": [
            [
                "8"
            ],
            [
                "8"
            ],
            [
                "8"
            ],
            [
                "8"
            ],
            [
                "8"
            ]
        ],
        "Icon": "/Game/Aki/UI/UIResources/Common/Image/MstSkill/T_MstSkil_Z_B10_UI.T_MstSkil_Z_B10_UI"
    },
    "Group": {
        "1": {
            "Id": 1,
            "Name": "凝夜白霜",
            "Icon": "/Game/Aki/UI/UIResources/Common/Image/IconElement/T_IconElementIce1.T_IconElementIce1",
            "Color": "41AEFBFF",
            "Set": {
                "2": {
                    "Desc": "冷凝伤害提升10%",
                    "Param": [
                        "10%"
                    ]
                },
                "5": {
                    "Desc": "使用普攻或重击时，冷凝伤害提升10%，该效果可叠加三层，持续15秒",
                    "Param": [
                        "30%",
                        "15"
                    ]
                }
            }
        },
        "5": {
            "Id": 5,
            "Name": "浮星祛暗",
            "Icon": "/Game/Aki/UI/UIResources/Common/Image/IconElement/T_IconElementLight1.T_IconElementLight1",
            "Color": "F8E56CFF",
            "Set": {
                "2": {
                    "Desc": "衍射伤害提升10%",
                    "Param": [
                        "10%"
                    ]
                },
                "5": {
                    "Desc": "使用变奏技能登场时，衍射伤害提升30%，持续15秒",
                    "Param": [
                        "30%"
                    ]
                }
            }
        }
    },
    "Rarity": [
        2,
        3,
        4,
        5
    ],
    "IntensityCode": 0,
    "MonsterInfo": 310000270,
    "Child": 391070105
}